eqdsk/__init__.py
eqdsk/_version.py
eqdsk/cli.py
eqdsk/cocos.py
eqdsk/errors.py
eqdsk/file.py
eqdsk/log.py
eqdsk/models.py
eqdsk/tools.py
eqdsk-0.7.0.dist-info/METADATA
eqdsk-0.7.0.dist-info/WHEEL
eqdsk-0.7.0.dist-info/entry_points.txt
eqdsk-0.7.0.dist-info/licenses/LICENSE
eqdsk-0.7.0.dist-info/RECORD
