Metadata-Version: 2.4
Name: eqdsk
Version: 0.7.0
Summary: A reader, writer and converter for the eqdsk format
Project-URL: Source, https://github.com/Fusion-Power-Plant-Framework/eqdsk
Project-URL: Documentation, https://github.com/Fusion-Power-Plant-Framework/eqdsk#readme
Project-URL: Issues, https://github.com/Fusion-Power-Plant-Framework/eqdsk/issues
Author: The Bluemira Developers
License-Expression: LGPL-2.1-or-later
License-File: LICENSE
Keywords: GEQDSK,cocos,eqdsk,tokamak
Classifier: Development Status :: 3 - Alpha
Classifier: Intended Audience :: Science/Research
Classifier: License :: OSI Approved :: GNU Lesser General Public License v2 or later (LGPLv2+)
Classifier: Natural Language :: English
Classifier: Operating System :: OS Independent
Classifier: Programming Language :: Python
Classifier: Topic :: Scientific/Engineering :: Physics
Classifier: Topic :: Software Development :: Libraries :: Python Modules
Requires-Python: >=3.10
Requires-Dist: click
Requires-Dist: fortranformat
Requires-Dist: numpy
Provides-Extra: cli
Requires-Dist: matplotlib; extra == 'cli'
Provides-Extra: dev
Requires-Dist: pre-commit; extra == 'dev'
Provides-Extra: docs
Requires-Dist: mkdocs; extra == 'docs'
Requires-Dist: mkdocs-gen-files; extra == 'docs'
Requires-Dist: mkdocs-literate-nav; extra == 'docs'
Requires-Dist: mkdocs-material; extra == 'docs'
Requires-Dist: mkdocs-section-index; extra == 'docs'
Requires-Dist: mkdocstrings[python]; extra == 'docs'
Provides-Extra: lint
Requires-Dist: mypy; extra == 'lint'
Requires-Dist: ruff; extra == 'lint'
Provides-Extra: test
Requires-Dist: pytest; extra == 'test'
Requires-Dist: pytest-cov; extra == 'test'
Requires-Dist: pytest-html; extra == 'test'
Requires-Dist: pytest-json-report; extra == 'test'
Requires-Dist: pytest-metadata; extra == 'test'
